GraphRicciCurvature/FormanRicci.py
GraphRicciCurvature/OllivierRicci.py
GraphRicciCurvature/__init__.py
GraphRicciCurvature/util.py
test/__init__.py
test/test_FormanRicci.py
test/test_OllivierRicci.py
GraphRicciCurvature-0.5.3.2.dist-info/LICENSE.txt
GraphRicciCurvature-0.5.3.2.dist-info/METADATA
GraphRicciCurvature-0.5.3.2.dist-info/WHEEL
GraphRicciCurvature-0.5.3.2.dist-info/top_level.txt
GraphRicciCurvature-0.5.3.2.dist-info/RECORD
