Metadata-Version: 2.1
Name: GraphRicciCurvature
Version: 0.5.3.2
Summary: Compute discrete Ricci curvatures and Ricci flow on NetworkX graphs.
Home-page: https://github.com/saibalmars/GraphRicciCurvature
Author: Chien-Chun Ni
Author-email: saibalmars@gmail.com
Classifier: Programming Language :: Python :: 3
Classifier: License :: OSI Approved :: Apache Software License
Classifier: Operating System :: OS Independent
License-File: LICENSE.txt
Requires-Dist: cython
Requires-Dist: numpy
Requires-Dist: scipy <=1.13.1
Requires-Dist: networkx >=2.0
Requires-Dist: pot >=0.8.0
Requires-Dist: packaging
Requires-Dist: networkit >=6.1
Requires-Dist: python-louvain
